python_openobserve/__init__.py
python_openobserve/openobserve.py
python_openobserve-0.4.2.dist-info/METADATA
python_openobserve-0.4.2.dist-info/WHEEL
python_openobserve-0.4.2.dist-info/entry_points.txt
python_openobserve-0.4.2.dist-info/licenses/LICENSES/CC-BY-4.0.txt
python_openobserve-0.4.2.dist-info/licenses/LICENSES/CC-BY-SA-4.0.txt
python_openobserve-0.4.2.dist-info/licenses/LICENSES/GPL-3.0-or-later.txt
python_openobserve-0.4.2.dist-info/RECORD
