Metadata-Version: 2.4
Name: python-openobserve
Version: 0.4.2
Summary: OpenObserve client for Python
License-File: LICENSES/CC-BY-4.0.txt
License-File: LICENSES/CC-BY-SA-4.0.txt
License-File: LICENSES/GPL-3.0-or-later.txt
Keywords: openobserve,elasticsearch,logging,unstructured data
Author: Justin Guese
Author-email: guese.justin@gmail.com
Requires-Python: >=3.10,<3.14
Classifier: Programming Language :: Python :: 3
Provides-Extra: ci
Provides-Extra: docs
Provides-Extra: fireducks
Provides-Extra: pandas
Provides-Extra: polars
Provides-Extra: tests
Requires-Dist: fireducks (==1.4.4) ; extra == "fireducks"
Requires-Dist: guarddog (==2.6.0) ; extra == "ci"
Requires-Dist: jmespath (==1.0.1) ; extra == "ci"
Requires-Dist: jmespath (==1.0.1) ; extra == "tests"
Requires-Dist: memray (==1.17.2) ; extra == "ci"
Requires-Dist: mkdocs (==1.6.1) ; extra == "docs"
Requires-Dist: mkdocs-material (==9.6.15) ; extra == "docs"
Requires-Dist: mkdocstrings (==0.29.1) ; extra == "docs"
Requires-Dist: mypy (==1.15.0) ; extra == "ci"
Requires-Dist: mypy-extensions (==1.0.0) ; extra == "ci"
Requires-Dist: pandas (==2.2.3) ; extra == "ci"
Requires-Dist: pandas (>=2.2) ; extra == "pandas"
Requires-Dist: pandas-stubs (==2.2.2.240807) ; extra == "ci"
Requires-Dist: polars (==1.30.0) ; extra == "polars"
Requires-Dist: pydantic (>=2.10,<3.0)
Requires-Dist: pytest (==8.3.5) ; extra == "ci"
Requires-Dist: pytest (==8.3.5) ; extra == "tests"
Requires-Dist: pytest-cov (==6.0.0) ; extra == "ci"
Requires-Dist: pytest-memray (==1.7.0) ; extra == "ci"
Requires-Dist: python-dotenv (==1.0.1) ; extra == "ci"
Requires-Dist: python-dotenv (==1.0.1) ; extra == "tests"
Requires-Dist: requests (>=2.32.4,<2.33.0)
Requires-Dist: sqlglot (>=26.4.0,<26.5.0)
Requires-Dist: types-jmespath (==1.0.2.20240106) ; extra == "ci"
Requires-Dist: types-requests (==2.32.0.20241016) ; extra == "ci"
Project-URL: Homepage, https://github.com/JustinGuese/python-openobserve
Project-URL: Repository, https://github.com/JustinGuese/python-openobserve
